{
  "type": "forge:conditional",
  "recipes": [
    {
      "conditions": [
        {
          "type": "forge:and",
          "values": [
            {
              "type": "forge:item_exists",
              "item": "functionalstorage:ender_drawer"
            }
          ]
        }
      ],
      "recipe": {
        "type": "minecraft:crafting_shaped",
        "key": {
          "C": {
            "tag": "forge:chests/ender"
          },
          "L": {
            "tag": "functionalstorage:drawer"
          },
          "P": {
            "tag": "minecraft:planks"
          }
        },
        "pattern": [
          "PPP",
          "LCL",
          "PPP"
        ],
        "result": {
          "item": "functionalstorage:ender_drawer"
        }
      }
    }
  ]
}